ce/__init__.py
ce/ce.py
contrast_enhancement-0.5.dist-info/DESCRIPTION.rst
contrast_enhancement-0.5.dist-info/METADATA
contrast_enhancement-0.5.dist-info/RECORD
contrast_enhancement-0.5.dist-info/WHEEL
contrast_enhancement-0.5.dist-info/metadata.json
contrast_enhancement-0.5.dist-info/top_level.txt
