Metadata-Version: 2.0
Name: contrast-enhancement
Version: 0.5
Summary: Enhance image contrast using standard deviation stretch
Home-page: https://github.com/ashvithashetty/contrast_enhancement
Author: Ashvitha Shetty
Author-email: ashvithashetty26@gmail.com
License: UNKNOWN
Download-URL: https://github.com/ashvithashetty/contrast_enhancement/archive/0.5.tar.gz
Platform: UNKNOWN
